Metadata-Version: 2.1
Name: PlotMyGoogleSheet28
Version: 0.0.1
Summary: This package will help you to plot a chart betweem any two columns from google sheet
Home-page: UNKNOWN
Author: Aditya Sisodiya
Author-email: adityasisodiya2803@gmail.com
License: MIT
Keywords: Graph Google-Sheet
Platform: UNKNOWN
Classifier: Development Status :: 3 - Alpha
Classifier: License :: OSI Approved :: MIT License
Classifier: Programming Language :: Python :: 3.7
Classifier: Topic :: Text Processing :: Linguistic
Classifier: Intended Audience :: Education
Classifier: Operating System :: Microsoft :: Windows :: Windows 10
